Metadata-Version: 2.1
Name: Anki-Overdrive-Windows
Version: 0.5.3
Summary: Anki Overdrive SDK for Windows
Home-page: https://github.com/jtg-code/anki-overdrive-windows-sdk/
Author: Julius Tiberius Gottschling and TKV
Author-email: juligo1008@gmail.com
License: Custom License
Keywords: anki,anki overdrive,bleak,overdrive,windows,bluetooth
Classifier: Development Status :: 5 - Production/Stable
Classifier: Intended Audience :: Education
Classifier: Operating System :: Microsoft :: Windows :: Windows 10
Classifier: License :: OSI Approved :: MIT License
Classifier: Programming Language :: Python :: 3
License-File: license.txt
